{
  "bid_details": {
    "bid_number": "GEM/2025/B/6009071",
    "bid_status": "Active",
    "quantity": "195",
    "bid_start_datetime": "11-03-2025 16:38:41",
    "bid_end_datetime": "01-04-2025 17:00:00",
    "bid_opening_datetime": "01-04-2025 17:30:00",
    "experience_with_gov_required": "Years",
    "bid_validity_days": "90"
  },
  "buyer_details": {
    "name": "Raj Kumar",
    "department": "Planning & Development Department Bihar",
    "organisation": "Planning And Development Department",
    "office": "Kaimur Bhabua"
  },
  "technical_evaluation": [
    {
      "sr_no": "1",
      "seller_name": "CONSCIOUS MIND SOLUTIONS PRIVATE LIMITED Under PMA",
      "offered_item": "-",
      "participated_on": "01-04-2025 13:05:27",
      "mse_mii_status": "Registered with designated Agency / Authority",
      "status": "Disqualified"
    },
    {
      "sr_no": "2",
      "seller_name": "G.K. ENTERPRISES Under PMA",
      "offered_item": "-",
      "participated_on": "31-03-2025 15:25:05",
      "mse_mii_status": "Offline upload",
      "status": "Qualified"
    },
    {
      "sr_no": "3",
      "seller_name": "PRASAD PSYCHO PRIVATE LIMITED Under PMA",
      "offered_item": "-",
      "participated_on": "01-04-2025 16:50:32",
      "mse_mii_status": "Registered with designated Agency / Authority",
      "status": "Disqualified"
    },
    {
      "sr_no": "4",
      "seller_name": "RANJIT SALES CORPORATION Under PMA",
      "offered_item": "-",
      "participated_on": "31-03-2025 15:53:29",
      "mse_mii_status": "Offline upload",
      "status": "Qualified"
    },
    {
      "sr_no": "5",
      "seller_name": "SAI SCIENTIFIC Under PMA",
      "offered_item": "-",
      "participated_on": "30-03-2025 14:22:30",
      "mse_mii_status": "Offline upload",
      "status": "Qualified"
    }
  ],
  "financial_evaluation": []
}